violoncello/__init__.py
violoncello/crawl.py
violoncello/data_pipeline.py
violoncello/drivers/__init__.py
violoncello/drivers/httpx_driver.py
violoncello/upload.py
violoncello-0.3.1.dist-info/LICENSE
violoncello-0.3.1.dist-info/METADATA
violoncello-0.3.1.dist-info/WHEEL
violoncello-0.3.1.dist-info/RECORD
