Metadata-Version: 2.3
Name: violoncello
Version: 0.3.1
Summary: 
Author: migo
Author-email: 1695587905@qq.com
Requires-Python: >=3.10,<3.13
Classifier: Programming Language :: Python :: 3
Classifier: Programming Language :: Python :: 3.10
Classifier: Programming Language :: Python :: 3.11
Classifier: Programming Language :: Python :: 3.12
Requires-Dist: audiomentations (>=0.40.0,<0.41.0)
Requires-Dist: httpx (>=0.28.1,<0.29.0)
Requires-Dist: hydra-core (>=1.0.7)
Requires-Dist: minio (>=7.2.15,<8.0.0)
Requires-Dist: numpy
Requires-Dist: pandas (>=2.2.3,<3.0.0)
Requires-Dist: pyarrow (>=19.0.1,<20.0.0)
Requires-Dist: tqdm (>=4.67.1,<5.0.0)
Requires-Dist: yarl (>=1.19.0,<2.0.0)
